{
  "func_80193F4": {
    "disasm": [
      "thumb_func_start func_80193F4",
      "func_80193F4:",
      "\tpush\t{lr}",
      "\tldr\tr1, .L_19410",
      "\tldr\tr0, .L_19414",
      "\tldrb\tr0, [r0, #1]",
      "\tlsl\tr0, r0, #2",
      "\tadd\tr0, r0, r1",
      "\tldr\tr0, [r0, #0]",
      "\tbl\t_call_via_r0",
      "\tlsl\tr0, r0, #24",
      "\tlsr\tr0, r0, #24",
      "\tpop\t{r1}",
      "\tbx\tr1",
      "\t.align\t2, 0",
      ".L_19410:",
      "\t.4byte\tsSnowmanWarioPoseTable",
      ".L_19414:",
      "\t.4byte\tgWarioData",
      "",
      ""
    ]
  },
  "func_8019418": {
    "disasm": [
      "thumb_func_start func_8019418",
      "func_8019418:",
      "\tldr\tr2, .L_1944c",
      "\tldr\tr3, .L_19450",
      "\tldrb\tr0, [r2, #31]",
      "\tlsl\tr1, r0, #1",
      "\tadd\tr1, r1, r0",
      "\tlsl\tr1, r1, #2",
      "\tadd\tr1, r1, r3",
      "\tldrb\tr0, [r2, #30]",
      "\tldrb\tr1, [r1, #8]",
      "\tcmp\tr0, r1",
      "\tbcc\t.L_19454",
      "\tmov\tr0, #0",
      "\tstrb\tr0, [r2, #30]",
      "\tldrb\tr0, [r2, #31]",
      "\tadd\tr0, #1",
      "\tstrb\tr0, [r2, #31]",
      "\tldrb\tr1, [r2, #31]",
      "\tlsl\tr0, r1, #1",
      "\tadd\tr0, r0, r1",
      "\tlsl\tr0, r0, #2",
      "\tadd\tr0, r0, r3",
      "\tldrb\tr0, [r0, #8]",
      "\tcmp\tr0, #0",
      "\tbne\t.L_19454",
      "\tmov\tr0, #7",
      "\tb\t.L_19456",
      ".L_1944c:",
      "\t.4byte\tgWarioData",
      ".L_19450:",
      "\t.4byte\tsUnk_833BAE0",
      ".L_19454:",
      "\tmov\tr0, #255\t@ 0xff",
      ".L_19456:",
      "\tbx\tlr",
      "",
      ""
    ]
  },
  "func_8019458": {
    "disasm": [
      "thumb_func_start func_8019458",
      "func_8019458:",
      "\tmov\tr0, #255\t@ 0xff",
      "\tbx\tlr",
      "",
      ""
    ]
  },
  "func_801945C": {
    "callees": [
      "func_806D4C0",
      "m4aSongNumStart"
    ],
    "disasm": [
      "thumb_func_start func_801945C",
      "func_801945C:",
      "\tpush\t{r4, lr}",
      "\tldr\tr4, .L_19490",
      "\tldrh\tr1, [r4, #28]",
      "\tmov\tr0, #1",
      "\tand\tr0, r1",
      "\tcmp\tr0, #0",
      "\tbeq\t.L_19494",
      "\tldrh\tr0, [r4, #20]",
      "\tadd\tr0, #20",
      "\tlsl\tr0, r0, #16",
      "\tlsr\tr0, r0, #16",
      "\tldrh\tr1, [r4, #18]",
      "\tbl\tfunc_806D4C0",
      "\tmov\tr1, #128\t@ 0x80",
      "\tlsl\tr1, r1, #17",
      "\tand\tr1, r0",
      "\tcmp\tr1, #0",
      "\tbne\t.L_19494",
      "\tldrh\tr0, [r4, #28]",
      "\tmov\tr1, #48\t@ 0x30",
      "\teor\tr0, r1",
      "\tand\tr0, r1",
      "\tstrh\tr0, [r4, #14]",
      "\tmov\tr0, #10",
      "\tb\t.L_19538",
      ".L_19490:",
      "\t.4byte\tgWarioData",
      ".L_19494:",
      "\tldr\tr0, .L_194a4",
      "\tldrh\tr1, [r0, #0]",
      "\tmov\tr0, #1",
      "\tand\tr0, r1",
      "\tcmp\tr0, #0",
      "\tbeq\t.L_194a8",
      "\tmov\tr0, #4",
      "\tb\t.L_19538",
      ".L_194a4:",
      "\t.4byte\tgButtonsPressed",
      ".L_194a8:",
      "\tldr\tr0, .L_194c8",
      "\tldr\tr1, .L_194cc",
      "\tldrh\tr3, [r0, #0]",
      "\tldrh\tr2, [r1, #14]",
      "\tadd\tr0, r3, #0",
      "\tand\tr0, r2",
      "\tadd\tr4, r1, #0",
      "\tcmp\tr0, #0",
      "\tbeq\t.L_194dc",
      "\tmov\tr0, #16",
      "\tand\tr0, r2",
      "\tcmp\tr0, #0",
      "\tbeq\t.L_194d0",
      "\tmov\tr0, #32",
      "\tstrh\tr0, [r4, #22]",
      "\tb\t.L_194f0",
      ".L_194c8:",
      "\t.4byte\tgButtonsHeld",
      ".L_194cc:",
      "\t.4byte\tgWarioData",
      ".L_194d0:",
      "\tldr\tr0, .L_194d8",
      "\tstrh\tr0, [r4, #22]",
      "\tb\t.L_194f0",
      "\t.align\t2, 0",
      ".L_194d8:",
      "\t.4byte\t0xFFE0",
      ".L_194dc:",
      "\tmov\tr0, #48\t@ 0x30",
      "\teor\tr0, r2",
      "\tand\tr0, r3",
      "\tlsl\tr0, r0, #16",
      "\tcmp\tr0, #0",
      "\tbeq\t.L_194ec",
      "\tmov\tr0, #9",
      "\tb\t.L_19538",
      ".L_194ec:",
      "\tmov\tr0, #8",
      "\tb\t.L_19538",
      ".L_194f0:",
      "\tadd\tr2, r4, #0",
      "\tldr\tr3, .L_19520",
      "\tldrb\tr0, [r2, #31]",
      "\tlsl\tr1, r0, #1",
      "\tadd\tr1, r1, r0",
      "\tlsl\tr1, r1, #2",
      "\tadd\tr1, r1, r3",
      "\tldrb\tr0, [r2, #30]",
      "\tldrb\tr1, [r1, #8]",
      "\tcmp\tr0, r1",
      "\tbcc\t.L_19536",
      "\tmov\tr0, #0",
      "\tstrb\tr0, [r2, #30]",
      "\tldrb\tr0, [r2, #31]",
      "\tadd\tr0, #1",
      "\tstrb\tr0, [r2, #31]",
      "\tlsl\tr0, r0, #24",
      "\tlsr\tr0, r0, #24",
      "\tcmp\tr0, #1",
      "\tbne\t.L_19524",
      "\tmov\tr0, #3",
      "\tbl\tm4aSongNumStart",
      "\tb\t.L_19536",
      ".L_19520:",
      "\t.4byte\tsUnk_833B9E4",
      ".L_19524:",
      "\tldrb\tr1, [r4, #31]",
      "\tlsl\tr0, r1, #1",
      "\tadd\tr0, r0, r1",
      "\tlsl\tr0, r0, #2",
      "\tadd\tr0, r0, r3",
      "\tldrb\tr0, [r0, #8]",
      "\tcmp\tr0, #0",
      "\tbne\t.L_19536",
      "\tstrb\tr0, [r4, #31]",
      ".L_19536:",
      "\tmov\tr0, #255\t@ 0xff",
      ".L_19538:",
      "\tpop\t{r4}",
      "\tpop\t{r1}",
      "\tbx\tr1",
      "",
      ""
    ]
  },
  "func_801953E": {
    "disasm": [
      "thumb_func_start func_801953E",
      "func_801953E:",
      "\t.align\t2, 0",
      "\tldr\tr2, .L_1957c",
      "\tldr\tr3, .L_19580",
      "\tldrb\tr0, [r2, #31]",
      "\tlsl\tr1, r0, #1",
      "\tadd\tr1, r1, r0",
      "\tlsl\tr1, r1, #2",
      "\tadd\tr1, r1, r3",
      "\tldrb\tr0, [r2, #30]",
      "\tldrb\tr1, [r1, #8]",
      "\tcmp\tr0, r1",
      "\tbcc\t.L_19584",
      "\tmov\tr0, #0",
      "\tstrb\tr0, [r2, #30]",
      "\tldrb\tr0, [r2, #31]",
      "\tadd\tr0, #1",
      "\tstrb\tr0, [r2, #31]",
      "\tldrb\tr1, [r2, #31]",
      "\tlsl\tr0, r1, #1",
      "\tadd\tr0, r0, r1",
      "\tlsl\tr0, r0, #2",
      "\tadd\tr0, r0, r3",
      "\tldrb\tr0, [r0, #8]",
      "\tcmp\tr0, #0",
      "\tbne\t.L_19584",
      "\tstrb\tr0, [r2, #0]",
      "\tmov\tr0, #96\t@ 0x60",
      "\tstrb\tr0, [r2, #4]",
      "\tmov\tr0, #2",
      "\tb\t.L_19586",
      "\t.align\t2, 0",
      ".L_1957c:",
      "\t.4byte\tgWarioData",
      ".L_19580:",
      "\t.4byte\tsUnk_833BA2C",
      ".L_19584:",
      "\tmov\tr0, #255\t@ 0xff",
      ".L_19586:",
      "\tbx\tlr",
      "",
      ""
    ]
  },
  "func_8019588": {
    "disasm": [
      "thumb_func_start func_8019588",
      "func_8019588:",
      "\tldr\tr2, .L_195c0",
      "\tldr\tr3, .L_195c4",
      "\tldrb\tr0, [r2, #31]",
      "\tlsl\tr1, r0, #1",
      "\tadd\tr1, r1, r0",
      "\tlsl\tr1, r1, #2",
      "\tadd\tr1, r1, r3",
      "\tldrb\tr0, [r2, #30]",
      "\tldrb\tr1, [r1, #8]",
      "\tcmp\tr0, r1",
      "\tbcc\t.L_195c8",
      "\tmov\tr0, #0",
      "\tstrb\tr0, [r2, #30]",
      "\tldrb\tr0, [r2, #31]",
      "\tadd\tr0, #1",
      "\tstrb\tr0, [r2, #31]",
      "\tldrb\tr1, [r2, #31]",
      "\tlsl\tr0, r1, #1",
      "\tadd\tr0, r0, r1",
      "\tlsl\tr0, r0, #2",
      "\tadd\tr0, r0, r3",
      "\tldrb\tr0, [r0, #8]",
      "\tcmp\tr0, #0",
      "\tbne\t.L_195c8",
      "\tmov\tr0, #1",
      "\tstrb\tr0, [r2, #8]",
      "\tmov\tr0, #254\t@ 0xfe",
      "\tb\t.L_195ca",
      ".L_195c0:",
      "\t.4byte\tgWarioData",
      ".L_195c4:",
      "\t.4byte\tsUnk_833BA74",
      ".L_195c8:",
      "\tmov\tr0, #255\t@ 0xff",
      ".L_195ca:",
      "\tbx\tlr",
      "",
      ""
    ]
  },
  "func_80195CC": {
    "disasm": [
      "thumb_func_start func_80195CC",
      "func_80195CC:",
      "\tpush\t{r4, lr}",
      "\tldr\tr0, .L_195ec",
      "\tldr\tr4, .L_195f0",
      "\tldrh\tr2, [r0, #0]",
      "\tldrh\tr1, [r4, #14]",
      "\tadd\tr3, r2, #0",
      "\tand\tr3, r1",
      "\tcmp\tr3, #0",
      "\tbeq\t.L_19600",
      "\tmov\tr0, #16",
      "\tand\tr0, r1",
      "\tcmp\tr0, #0",
      "\tbeq\t.L_195f4",
      "\tmov\tr0, #32",
      "\tstrh\tr0, [r4, #22]",
      "\tb\t.L_19612",
      ".L_195ec:",
      "\t.4byte\tgButtonsHeld",
      ".L_195f0:",
      "\t.4byte\tgWarioData",
      ".L_195f4:",
      "\tldr\tr0, .L_195fc",
      "\tstrh\tr0, [r4, #22]",
      "\tb\t.L_19612",
      "\t.align\t2, 0",
      ".L_195fc:",
      "\t.4byte\t0xFFE0",
      ".L_19600:",
      "\tmov\tr0, #48\t@ 0x30",
      "\teor\tr1, r0",
      "\tadd\tr0, r1, #0",
      "\tand\tr0, r2",
      "\tlsl\tr0, r0, #16",
      "\tcmp\tr0, #0",
      "\tbeq\t.L_19610",
      "\tstrh\tr1, [r4, #14]",
      ".L_19610:",
      "\tstrh\tr3, [r4, #22]",
      ".L_19612:",
      "\tmov\tr0, #255\t@ 0xff",
      "\tpop\t{r4}",
      "\tpop\t{r1}",
      "\tbx\tr1",
      "",
      ""
    ]
  },
  "func_801961A": {
    "disasm": [
      "thumb_func_start func_801961A",
      "func_801961A:",
      "\t.align\t2, 0",
      "\tldr\tr0, .L_19628",
      "\tldrb\tr0, [r0, #30]",
      "\tcmp\tr0, #29",
      "\tbls\t.L_1962c",
      "\tmov\tr0, #8",
      "\tb\t.L_19658",
      ".L_19628:",
      "\t.4byte\tgWarioData",
      ".L_1962c:",
      "\tldr\tr2, .L_1965c",
      "\tldr\tr3, .L_19660",
      "\tldrb\tr0, [r2, #2]",
      "\tlsl\tr0, r0, #3",
      "\tadd\tr0, r0, r3",
      "\tldrb\tr1, [r2, #1]",
      "\tldrh\tr0, [r0, #4]",
      "\tcmp\tr1, r0",
      "\tbcc\t.L_19656",
      "\tmov\tr0, #0",
      "\tstrb\tr0, [r2, #1]",
      "\tldrb\tr0, [r2, #2]",
      "\tadd\tr0, #1",
      "\tstrb\tr0, [r2, #2]",
      "\tldrb\tr0, [r2, #2]",
      "\tlsl\tr0, r0, #3",
      "\tadd\tr0, r0, r3",
      "\tldrh\tr0, [r0, #4]",
      "\tcmp\tr0, #0",
      "\tbne\t.L_19656",
      "\tstrb\tr0, [r2, #2]",
      ".L_19656:",
      "\tmov\tr0, #255\t@ 0xff",
      ".L_19658:",
      "\tbx\tlr",
      "\t.align\t2, 0",
      ".L_1965c:",
      "\t.4byte\tgUnk_3001930",
      ".L_19660:",
      "\t.4byte\tsUnk_82E04C4",
      "",
      ""
    ]
  },
  "func_8019664": {
    "disasm": [
      "thumb_func_start func_8019664",
      "func_8019664:",
      "\tldr\tr2, .L_19698",
      "\tldr\tr3, .L_1969c",
      "\tldrb\tr0, [r2, #31]",
      "\tlsl\tr1, r0, #1",
      "\tadd\tr1, r1, r0",
      "\tlsl\tr1, r1, #2",
      "\tadd\tr1, r1, r3",
      "\tldrb\tr0, [r2, #30]",
      "\tldrb\tr1, [r1, #8]",
      "\tcmp\tr0, r1",
      "\tbcc\t.L_196a0",
      "\tmov\tr0, #0",
      "\tstrb\tr0, [r2, #30]",
      "\tldrb\tr0, [r2, #31]",
      "\tadd\tr0, #1",
      "\tstrb\tr0, [r2, #31]",
      "\tldrb\tr1, [r2, #31]",
      "\tlsl\tr0, r1, #1",
      "\tadd\tr0, r0, r1",
      "\tlsl\tr0, r0, #2",
      "\tadd\tr0, r0, r3",
      "\tldrb\tr0, [r0, #8]",
      "\tcmp\tr0, #0",
      "\tbne\t.L_196a0",
      "\tmov\tr0, #8",
      "\tb\t.L_196a2",
      ".L_19698:",
      "\t.4byte\tgWarioData",
      ".L_1969c:",
      "\t.4byte\tsUnk_833BB10",
      ".L_196a0:",
      "\tmov\tr0, #255\t@ 0xff",
      ".L_196a2:",
      "\tbx\tlr",
      "",
      ""
    ]
  },
  "func_80196A4": {
    "disasm": [
      "thumb_func_start func_80196A4",
      "func_80196A4:",
      "\tpush\t{r4, lr}",
      "\tldr\tr3, .L_196c4",
      "\tldrh\tr2, [r3, #28]",
      "\tmov\tr4, #1",
      "\tadd\tr0, r4, #0",
      "\tand\tr0, r2",
      "\tcmp\tr0, #0",
      "\tbeq\t.L_196c8",
      "\tmov\tr1, #48\t@ 0x30",
      "\tadd\tr0, r2, #0",
      "\teor\tr0, r1",
      "\tand\tr0, r1",
      "\tstrh\tr0, [r3, #14]",
      "\tmov\tr0, #10",
      "\tb\t.L_19704",
      "\t.align\t2, 0",
      ".L_196c4:",
      "\t.4byte\tgWarioData",
      ".L_196c8:",
      "\tldr\tr0, .L_196d8",
      "\tldrh\tr1, [r0, #0]",
      "\tadd\tr0, r4, #0",
      "\tand\tr0, r1",
      "\tcmp\tr0, #0",
      "\tbeq\t.L_196dc",
      "\tmov\tr0, #4",
      "\tb\t.L_19704",
      ".L_196d8:",
      "\t.4byte\tgButtonsPressed",
      ".L_196dc:",
      "\tldr\tr0, .L_196f0",
      "\tldrh\tr2, [r0, #0]",
      "\tldrh\tr1, [r3, #14]",
      "\tadd\tr0, r2, #0",
      "\tand\tr0, r1",
      "\tcmp\tr0, #0",
      "\tbeq\t.L_196f4",
      "\tmov\tr0, #2",
      "\tb\t.L_19704",
      "\t.align\t2, 0",
      ".L_196f0:",
      "\t.4byte\tgButtonsHeld",
      ".L_196f4:",
      "\tmov\tr0, #48\t@ 0x30",
      "\teor\tr0, r1",
      "\tand\tr0, r2",
      "\tcmp\tr0, #0",
      "\tbne\t.L_19702",
      "\tmov\tr0, #255\t@ 0xff",
      "\tb\t.L_19704",
      ".L_19702:",
      "\tmov\tr0, #9",
      ".L_19704:",
      "\tpop\t{r4}",
      "\tpop\t{r1}",
      "\tbx\tr1",
      "",
      ""
    ]
  },
  "func_801970A": {
    "disasm": [
      "thumb_func_start func_801970A",
      "func_801970A:",
      "\t.align\t2, 0",
      "\tldr\tr2, .L_19740",
      "\tldr\tr3, .L_19744",
      "\tldrb\tr0, [r2, #31]",
      "\tlsl\tr1, r0, #1",
      "\tadd\tr1, r1, r0",
      "\tlsl\tr1, r1, #2",
      "\tadd\tr1, r1, r3",
      "\tldrb\tr0, [r2, #30]",
      "\tldrb\tr1, [r1, #8]",
      "\tcmp\tr0, r1",
      "\tbcc\t.L_19748",
      "\tmov\tr0, #0",
      "\tstrb\tr0, [r2, #30]",
      "\tldrb\tr0, [r2, #31]",
      "\tadd\tr0, #1",
      "\tstrb\tr0, [r2, #31]",
      "\tldrb\tr1, [r2, #31]",
      "\tlsl\tr0, r1, #1",
      "\tadd\tr0, r0, r1",
      "\tlsl\tr0, r0, #2",
      "\tadd\tr0, r0, r3",
      "\tldrb\tr0, [r0, #8]",
      "\tcmp\tr0, #0",
      "\tbne\t.L_19748",
      "\tmov\tr0, #8",
      "\tb\t.L_1974a",
      ".L_19740:",
      "\t.4byte\tgWarioData",
      ".L_19744:",
      "\t.4byte\tsUnk_833BBA0",
      ".L_19748:",
      "\tmov\tr0, #255\t@ 0xff",
      ".L_1974a:",
      "\tbx\tlr",
      "",
      ""
    ]
  },
  "func_801974C": {
    "disasm": [
      "thumb_func_start func_801974C",
      "func_801974C:",
      "\tldr\tr2, .L_1975c",
      "\tldrh\tr1, [r2, #14]",
      "\tmov\tr0, #16",
      "\tand\tr0, r1",
      "\tcmp\tr0, #0",
      "\tbeq\t.L_19760",
      "\tmov\tr0, #64\t@ 0x40",
      "\tb\t.L_19762",
      ".L_1975c:",
      "\t.4byte\tgWarioData",
      ".L_19760:",
      "\tldr\tr0, .L_19798",
      ".L_19762:",
      "\tstrh\tr0, [r2, #22]",
      "\tldr\tr3, .L_1979c",
      "\tldrb\tr0, [r2, #31]",
      "\tlsl\tr1, r0, #1",
      "\tadd\tr1, r1, r0",
      "\tlsl\tr1, r1, #2",
      "\tadd\tr1, r1, r3",
      "\tldrb\tr0, [r2, #30]",
      "\tldrb\tr1, [r1, #8]",
      "\tcmp\tr0, r1",
      "\tbcc\t.L_197a0",
      "\tmov\tr0, #0",
      "\tstrb\tr0, [r2, #30]",
      "\tldrb\tr0, [r2, #31]",
      "\tadd\tr0, #1",
      "\tstrb\tr0, [r2, #31]",
      "\tldrb\tr1, [r2, #31]",
      "\tlsl\tr0, r1, #1",
      "\tadd\tr0, r0, r1",
      "\tlsl\tr0, r0, #2",
      "\tadd\tr0, r0, r3",
      "\tldrb\tr0, [r0, #8]",
      "\tcmp\tr0, #0",
      "\tbne\t.L_197a0",
      "\tmov\tr0, #12",
      "\tb\t.L_197a2",
      "\t.align\t2, 0",
      ".L_19798:",
      "\t.4byte\t0xFFC0",
      ".L_1979c:",
      "\t.4byte\tsUnk_833BBC4",
      ".L_197a0:",
      "\tmov\tr0, #255\t@ 0xff",
      ".L_197a2:",
      "\tbx\tlr",
      "",
      ""
    ]
  },
  "func_80197A4": {
    "disasm": [
      "thumb_func_start func_80197A4",
      "func_80197A4:",
      "\tldr\tr2, .L_197b4",
      "\tldrh\tr1, [r2, #14]",
      "\tmov\tr0, #16",
      "\tand\tr0, r1",
      "\tcmp\tr0, #0",
      "\tbeq\t.L_197b8",
      "\tmov\tr0, #64\t@ 0x40",
      "\tb\t.L_197ba",
      ".L_197b4:",
      "\t.4byte\tgWarioData",
      ".L_197b8:",
      "\tldr\tr0, .L_197f0",
      ".L_197ba:",
      "\tstrh\tr0, [r2, #22]",
      "\tldr\tr3, .L_197f4",
      "\tldrb\tr0, [r2, #31]",
      "\tlsl\tr1, r0, #1",
      "\tadd\tr1, r1, r0",
      "\tlsl\tr1, r1, #2",
      "\tadd\tr1, r1, r3",
      "\tldrb\tr0, [r2, #30]",
      "\tldrb\tr1, [r1, #8]",
      "\tcmp\tr0, r1",
      "\tbcc\t.L_197f8",
      "\tmov\tr0, #0",
      "\tstrb\tr0, [r2, #30]",
      "\tldrb\tr0, [r2, #31]",
      "\tadd\tr0, #1",
      "\tstrb\tr0, [r2, #31]",
      "\tldrb\tr1, [r2, #31]",
      "\tlsl\tr0, r1, #1",
      "\tadd\tr0, r0, r1",
      "\tlsl\tr0, r0, #2",
      "\tadd\tr0, r0, r3",
      "\tldrb\tr0, [r0, #8]",
      "\tcmp\tr0, #0",
      "\tbne\t.L_197f8",
      "\tmov\tr0, #13",
      "\tb\t.L_197fa",
      "\t.align\t2, 0",
      ".L_197f0:",
      "\t.4byte\t0xFFC0",
      ".L_197f4:",
      "\t.4byte\tsUnk_833BBC4",
      ".L_197f8:",
      "\tmov\tr0, #255\t@ 0xff",
      ".L_197fa:",
      "\tbx\tlr",
      "",
      ""
    ]
  },
  "func_80197FC": {
    "disasm": [
      "thumb_func_start func_80197FC",
      "func_80197FC:",
      "\tldr\tr2, .L_1980c",
      "\tldrh\tr1, [r2, #14]",
      "\tmov\tr0, #16",
      "\tand\tr0, r1",
      "\tcmp\tr0, #0",
      "\tbeq\t.L_19810",
      "\tmov\tr0, #96\t@ 0x60",
      "\tb\t.L_19812",
      ".L_1980c:",
      "\t.4byte\tgWarioData",
      ".L_19810:",
      "\tldr\tr0, .L_19820",
      ".L_19812:",
      "\tstrh\tr0, [r2, #22]",
      "\tldrb\tr0, [r2, #10]",
      "\tcmp\tr0, #47\t@ 0x2f",
      "\tbls\t.L_19824",
      "\tmov\tr0, #14",
      "\tb\t.L_1985a",
      "\t.align\t2, 0",
      ".L_19820:",
      "\t.4byte\t0xFFA0",
      ".L_19824:",
      "\tadd\tr0, #1",
      "\tstrb\tr0, [r2, #10]",
      "\tldr\tr3, .L_1985c",
      "\tldrb\tr1, [r2, #31]",
      "\tlsl\tr0, r1, #1",
      "\tadd\tr0, r0, r1",
      "\tlsl\tr0, r0, #2",
      "\tadd\tr0, r0, r3",
      "\tldrb\tr1, [r2, #30]",
      "\tldrb\tr0, [r0, #8]",
      "\tcmp\tr1, r0",
      "\tbcc\t.L_19858",
      "\tmov\tr0, #0",
      "\tstrb\tr0, [r2, #30]",
      "\tldrb\tr0, [r2, #31]",
      "\tadd\tr0, #1",
      "\tstrb\tr0, [r2, #31]",
      "\tldrb\tr1, [r2, #31]",
      "\tlsl\tr0, r1, #1",
      "\tadd\tr0, r0, r1",
      "\tlsl\tr0, r0, #2",
      "\tadd\tr0, r0, r3",
      "\tldrb\tr0, [r0, #8]",
      "\tcmp\tr0, #0",
      "\tbne\t.L_19858",
      "\tstrb\tr0, [r2, #31]",
      ".L_19858:",
      "\tmov\tr0, #255\t@ 0xff",
      ".L_1985a:",
      "\tbx\tlr",
      ".L_1985c:",
      "\t.4byte\tsUnk_833BC18",
      "",
      ""
    ]
  },
  "func_8019860": {
    "disasm": [
      "thumb_func_start func_8019860",
      "func_8019860:",
      "\tldr\tr2, .L_19870",
      "\tldrh\tr1, [r2, #14]",
      "\tmov\tr0, #16",
      "\tand\tr0, r1",
      "\tcmp\tr0, #0",
      "\tbeq\t.L_19874",
      "\tmov\tr0, #96\t@ 0x60",
      "\tb\t.L_19876",
      ".L_19870:",
      "\t.4byte\tgWarioData",
      ".L_19874:",
      "\tldr\tr0, .L_19884",
      ".L_19876:",
      "\tstrh\tr0, [r2, #22]",
      "\tldrb\tr0, [r2, #10]",
      "\tcmp\tr0, #47\t@ 0x2f",
      "\tbls\t.L_19888",
      "\tmov\tr0, #15",
      "\tb\t.L_198be",
      "\t.align\t2, 0",
      ".L_19884:",
      "\t.4byte\t0xFFA0",
      ".L_19888:",
      "\tadd\tr0, #1",
      "\tstrb\tr0, [r2, #10]",
      "\tldr\tr3, .L_198c0",
      "\tldrb\tr1, [r2, #31]",
      "\tlsl\tr0, r1, #1",
      "\tadd\tr0, r0, r1",
      "\tlsl\tr0, r0, #2",
      "\tadd\tr0, r0, r3",
      "\tldrb\tr1, [r2, #30]",
      "\tldrb\tr0, [r0, #8]",
      "\tcmp\tr1, r0",
      "\tbcc\t.L_198bc",
      "\tmov\tr0, #0",
      "\tstrb\tr0, [r2, #30]",
      "\tldrb\tr0, [r2, #31]",
      "\tadd\tr0, #1",
      "\tstrb\tr0, [r2, #31]",
      "\tldrb\tr1, [r2, #31]",
      "\tlsl\tr0, r1, #1",
      "\tadd\tr0, r0, r1",
      "\tlsl\tr0, r0, #2",
      "\tadd\tr0, r0, r3",
      "\tldrb\tr0, [r0, #8]",
      "\tcmp\tr0, #0",
      "\tbne\t.L_198bc",
      "\tstrb\tr0, [r2, #31]",
      ".L_198bc:",
      "\tmov\tr0, #255\t@ 0xff",
      ".L_198be:",
      "\tbx\tlr",
      ".L_198c0:",
      "\t.4byte\tsUnk_833BC18",
      "",
      ""
    ]
  },
  "func_80198C4": {
    "disasm": [
      "thumb_func_start func_80198C4",
      "func_80198C4:",
      "\tldr\tr2, .L_198d4",
      "\tldrh\tr1, [r2, #14]",
      "\tmov\tr0, #16",
      "\tand\tr0, r1",
      "\tcmp\tr0, #0",
      "\tbeq\t.L_198d8",
      "\tmov\tr0, #128\t@ 0x80",
      "\tb\t.L_198da",
      ".L_198d4:",
      "\t.4byte\tgWarioData",
      ".L_198d8:",
      "\tldr\tr0, .L_19910",
      ".L_198da:",
      "\tstrh\tr0, [r2, #22]",
      "\tldr\tr3, .L_19914",
      "\tldrb\tr0, [r2, #31]",
      "\tlsl\tr1, r0, #1",
      "\tadd\tr1, r1, r0",
      "\tlsl\tr1, r1, #2",
      "\tadd\tr1, r1, r3",
      "\tldrb\tr0, [r2, #30]",
      "\tldrb\tr1, [r1, #8]",
      "\tcmp\tr0, r1",
      "\tbcc\t.L_1990c",
      "\tmov\tr0, #0",
      "\tstrb\tr0, [r2, #30]",
      "\tldrb\tr0, [r2, #31]",
      "\tadd\tr0, #1",
      "\tstrb\tr0, [r2, #31]",
      "\tldrb\tr1, [r2, #31]",
      "\tlsl\tr0, r1, #1",
      "\tadd\tr0, r0, r1",
      "\tlsl\tr0, r0, #2",
      "\tadd\tr0, r0, r3",
      "\tldrb\tr0, [r0, #8]",
      "\tcmp\tr0, #0",
      "\tbne\t.L_1990c",
      "\tstrb\tr0, [r2, #31]",
      ".L_1990c:",
      "\tmov\tr0, #255\t@ 0xff",
      "\tbx\tlr",
      ".L_19910:",
      "\t.4byte\t0xFF80",
      ".L_19914:",
      "\t.4byte\tsUnk_833BC54",
      "",
      ""
    ]
  },
  "func_8019918": {
    "disasm": [
      "thumb_func_start func_8019918",
      "func_8019918:",
      "\tldr\tr2, .L_19928",
      "\tldrh\tr1, [r2, #14]",
      "\tmov\tr0, #16",
      "\tand\tr0, r1",
      "\tcmp\tr0, #0",
      "\tbeq\t.L_1992c",
      "\tmov\tr0, #128\t@ 0x80",
      "\tb\t.L_1992e",
      ".L_19928:",
      "\t.4byte\tgWarioData",
      ".L_1992c:",
      "\tldr\tr0, .L_19964",
      ".L_1992e:",
      "\tstrh\tr0, [r2, #22]",
      "\tldr\tr3, .L_19968",
      "\tldrb\tr0, [r2, #31]",
      "\tlsl\tr1, r0, #1",
      "\tadd\tr1, r1, r0",
      "\tlsl\tr1, r1, #2",
      "\tadd\tr1, r1, r3",
      "\tldrb\tr0, [r2, #30]",
      "\tldrb\tr1, [r1, #8]",
      "\tcmp\tr0, r1",
      "\tbcc\t.L_19960",
      "\tmov\tr0, #0",
      "\tstrb\tr0, [r2, #30]",
      "\tldrb\tr0, [r2, #31]",
      "\tadd\tr0, #1",
      "\tstrb\tr0, [r2, #31]",
      "\tldrb\tr1, [r2, #31]",
      "\tlsl\tr0, r1, #1",
      "\tadd\tr0, r0, r1",
      "\tlsl\tr0, r0, #2",
      "\tadd\tr0, r0, r3",
      "\tldrb\tr0, [r0, #8]",
      "\tcmp\tr0, #0",
      "\tbne\t.L_19960",
      "\tstrb\tr0, [r2, #31]",
      ".L_19960:",
      "\tmov\tr0, #255\t@ 0xff",
      "\tbx\tlr",
      ".L_19964:",
      "\t.4byte\t0xFF80",
      ".L_19968:",
      "\t.4byte\tsUnk_833BC54",
      "",
      ""
    ]
  },
  "func_801996C": {
    "callees": [
      "func_8010230",
      "m4aSongNumStart",
      "VoiceSetPlay",
      "ScreenShakeRequestY"
    ],
    "calledBy": [
      "func_8019B60"
    ],
    "disasm": [
      "thumb_func_start func_801996C",
      "func_801996C:",
      "\tpush\t{r4, lr}",
      "\tlsl\tr0, r0, #24",
      "\tlsr\tr4, r0, #24",
      "\tbl\tfunc_8010230",
      "\tcmp\tr4, #0",
      "\tbne\t.L_19998",
      "\tldr\tr0, .L_19994",
      "\tldrb\tr0, [r0, #26]",
      "\tcmp\tr0, #2",
      "\tbne\t.L_19984",
      "\tmov\tr4, #1",
      ".L_19984:",
      "\tmov\tr0, #175\t@ 0xaf",
      "\tlsl\tr0, r0, #1",
      "\tbl\tm4aSongNumStart",
      "\tmov\tr0, #4",
      "\tbl\tVoiceSetPlay",
      "\tb\t.L_199b0",
      ".L_19994:",
      "\t.4byte\tgWarioDataCopy",
      ".L_19998:",
      "\tcmp\tr4, #253\t@ 0xfd",
      "\tbne\t.L_199b0",
      "\tldr\tr1, .L_199c4",
      "\tldr\tr0, .L_199c8",
      "\tldrb\tr0, [r0, #1]",
      "\tlsl\tr0, r0, #3",
      "\tadd\tr1, #7",
      "\tadd\tr0, r0, r1",
      "\tldrb\tr0, [r0, #0]",
      "\tcmp\tr0, #2",
      "\tbeq\t.L_199b0",
      "\tb\t.L_19ac2",
      ".L_199b0:",
      "\tcmp\tr4, #10",
      "\tbeq\t.L_19a88",
      "\tcmp\tr4, #10",
      "\tbgt\t.L_199cc",
      "\tcmp\tr4, #3",
      "\tbeq\t.L_19a6c",
      "\tcmp\tr4, #9",
      "\tbne\t.L_199c2",
      "\tb\t.L_19aa4",
      ".L_199c2:",
      "\tb\t.L_19aaa",
      ".L_199c4:",
      "\t.4byte\tsUnk_82DDA90",
      ".L_199c8:",
      "\t.4byte\tgWarioDataCopy",
      ".L_199cc:",
      "\tcmp\tr4, #253\t@ 0xfd",
      "\tbeq\t.L_19a14",
      "\tcmp\tr4, #254\t@ 0xfe",
      "\tbne\t.L_19aaa",
      "\tldr\tr2, .L_199e4",
      "\tldrb\tr0, [r2, #1]",
      "\tcmp\tr0, #0",
      "\tbne\t.L_199ec",
      "\tldr\tr1, .L_199e8",
      "\tmov\tr0, #1",
      "\tstrb\tr0, [r1, #1]",
      "\tb\t.L_19aae",
      ".L_199e4:",
      "\t.4byte\tgWarioDataCopy",
      ".L_199e8:",
      "\t.4byte\tgWarioData",
      ".L_199ec:",
      "\tcmp\tr0, #9",
      "\tbls\t.L_199fc",
      "\tldr\tr0, .L_199f8",
      "\tldrb\tr1, [r0, #1]",
      "\tadd\tr1, #1",
      "\tb\t.L_19a5e",
      ".L_199f8:",
      "\t.4byte\tgWarioData",
      ".L_199fc:",
      "\tldr\tr1, .L_19a10",
      "\tmov\tr0, #5",
      "\tstrb\tr0, [r1, #1]",
      "\tldrb\tr0, [r2, #8]",
      "\tcmp\tr0, #0",
      "\tbeq\t.L_19aae",
      "\tmov\tr0, #96\t@ 0x60",
      "\tstrh\tr0, [r1, #24]",
      "\tb\t.L_19aae",
      "\t.align\t2, 0",
      ".L_19a10:",
      "\t.4byte\tgWarioData",
      ".L_19a14:",
      "\tldr\tr2, .L_19a24",
      "\tldrb\tr0, [r2, #1]",
      "\tcmp\tr0, #1",
      "\tbne\t.L_19a2c",
      "\tldr\tr1, .L_19a28",
      "\tmov\tr0, #7",
      "\tstrb\tr0, [r1, #1]",
      "\tb\t.L_19aae",
      ".L_19a24:",
      "\t.4byte\tgWarioDataCopy",
      ".L_19a28:",
      "\t.4byte\tgWarioData",
      ".L_19a2c:",
      "\tcmp\tr0, #5",
      "\tbne\t.L_19a54",
      "\tldr\tr1, .L_19a4c",
      "\tmov\tr0, #6",
      "\tstrb\tr0, [r1, #1]",
      "\tldr\tr1, .L_19a50",
      "\tmov\tr0, #4",
      "\tstrb\tr0, [r1, #0]",
      "\tmov\tr0, #64\t@ 0x40",
      "\tmov\tr1, #0",
      "\tbl\tScreenShakeRequestY",
      "\tmov\tr0, #24",
      "\tbl\tm4aSongNumStart",
      "\tb\t.L_19aae",
      ".L_19a4c:",
      "\t.4byte\tgWarioData",
      ".L_19a50:",
      "\t.4byte\tgUnk_3001930",
      ".L_19a54:",
      "\tcmp\tr0, #9",
      "\tbls\t.L_19aae",
      "\tldr\tr0, .L_19a68",
      "\tldrb\tr1, [r0, #1]",
      "\tsub\tr1, #1",
      ".L_19a5e:",
      "\tstrb\tr1, [r0, #1]",
      "\tldrh\tr1, [r2, #22]",
      "\tstrh\tr1, [r0, #22]",
      "\tb\t.L_19aae",
      "\t.align\t2, 0",
      ".L_19a68:",
      "\t.4byte\tgWarioData",
      ".L_19a6c:",
      "\tldr\tr0, .L_19a80",
      "\tstrb\tr4, [r0, #1]",
      "\tldr\tr0, .L_19a84",
      "\tbl\tm4aSongNumStart",
      "\tmov\tr0, #0",
      "\tbl\tVoiceSetPlay",
      "\tb\t.L_19aae",
      "\t.align\t2, 0",
      ".L_19a80:",
      "\t.4byte\tgWarioData",
      ".L_19a84:",
      "\t.4byte\t0x15F",
      ".L_19a88:",
      "\tldr\tr0, .L_19a9c",
      "\tstrb\tr4, [r0, #1]",
      "\tldr\tr0, .L_19aa0",
      "\tldrb\tr0, [r0, #1]",
      "\tcmp\tr0, #9",
      "\tbhi\t.L_19aae",
      "\tmov\tr0, #45\t@ 0x2d",
      "\tbl\tm4aSongNumStart",
      "\tb\t.L_19aae",
      ".L_19a9c:",
      "\t.4byte\tgWarioData",
      ".L_19aa0:",
      "\t.4byte\tgWarioDataCopy",
      ".L_19aa4:",
      "\tldr\tr1, .L_19ac8",
      "\tmov\tr0, #1",
      "\tstrb\tr0, [r1, #3]",
      ".L_19aaa:",
      "\tldr\tr0, .L_19ac8",
      "\tstrb\tr4, [r0, #1]",
      ".L_19aae:",
      "\tldr\tr1, .L_19ac8",
      "\tldrb\tr0, [r1, #1]",
      "\tsub\tr0, #12",
      "\tlsl\tr0, r0, #24",
      "\tlsr\tr0, r0, #24",
      "\tcmp\tr0, #1",
      "\tbhi\t.L_19ac2",
      "\tldr\tr0, .L_19acc",
      "\tldrb\tr0, [r0, #10]",
      "\tstrb\tr0, [r1, #10]",
      ".L_19ac2:",
      "\tpop\t{r4}",
      "\tpop\t{r0}",
      "\tbx\tr0",
      ".L_19ac8:",
      "\t.4byte\tgWarioData",
      ".L_19acc:",
      "\t.4byte\tgWarioDataCopy",
      "",
      ""
    ]
  },
  "func_8019AD0": {
    "callees": [
      "func_800FE58",
      "func_800FDBC"
    ],
    "disasm": [
      "thumb_func_start func_8019AD0",
      "func_8019AD0:",
      "\tpush\t{r4, lr}",
      "\tldr\tr3, .L_19b38",
      "\tldr\tr2, .L_19b3c",
      "\tldr\tr4, .L_19b40",
      "\tldrb\tr0, [r4, #1]",
      "\tlsl\tr0, r0, #3",
      "\tadd\tr1, r2, #1",
      "\tadd\tr0, r0, r1",
      "\tldrb\tr0, [r0, #0]",
      "\tstrb\tr0, [r3, #8]",
      "\tldrb\tr0, [r4, #1]",
      "\tlsl\tr0, r0, #3",
      "\tadd\tr1, r2, #2",
      "\tadd\tr0, r0, r1",
      "\tldrb\tr0, [r0, #0]",
      "\tstrb\tr0, [r3, #9]",
      "\tldrb\tr0, [r4, #1]",
      "\tlsl\tr0, r0, #3",
      "\tadd\tr2, #3",
      "\tadd\tr0, r0, r2",
      "\tldrb\tr0, [r0, #0]",
      "\tstrb\tr0, [r3, #10]",
      "\tbl\tfunc_800FE58",
      "\tmov\tr2, #0",
      "\tldrb\tr0, [r4, #26]",
      "\tcmp\tr0, #2",
      "\tbne\t.L_19b16",
      "\tldrh\tr1, [r4, #24]",
      "\tlsl\tr0, r1, #16",
      "\tasr\tr0, r0, #19",
      "\tlsl\tr0, r0, #16",
      "\tlsr\tr2, r0, #16",
      "\tsub\tr1, #8",
      "\tstrh\tr1, [r4, #24]",
      ".L_19b16:",
      "\tmov\tr1, #24",
      "\tldrsh\tr0, [r4, r1]",
      "\tmov\tr1, #128\t@ 0x80",
      "\tneg\tr1, r1",
      "\tcmp\tr0, r1",
      "\tbge\t.L_19b24",
      "\tstrh\tr1, [r4, #24]",
      ".L_19b24:",
      "\tldrh\tr0, [r4, #20]",
      "\tsub\tr0, r0, r2",
      "\tstrh\tr0, [r4, #20]",
      "\tldrb\tr0, [r4, #26]",
      "\tcmp\tr0, #0",
      "\tbne\t.L_19b44",
      "\tbl\tfunc_800FDBC",
      "\tb\t.L_19b46",
      "\t.align\t2, 0",
      ".L_19b38:",
      "\t.4byte\tgUnk_3001918",
      ".L_19b3c:",
      "\t.4byte\tsUnk_82DDA90",
      ".L_19b40:",
      "\t.4byte\tgWarioData",
      ".L_19b44:",
      "\tldrh\tr0, [r4, #22]",
      ".L_19b46:",
      "\tlsl\tr0, r0, #16",
      "\tasr\tr0, r0, #19",
      "\tlsl\tr0, r0, #16",
      "\tlsr\tr2, r0, #16",
      "\tldr\tr1, .L_19b5c",
      "\tldrh\tr0, [r1, #18]",
      "\tadd\tr0, r0, r2",
      "\tstrh\tr0, [r1, #18]",
      "\tpop\t{r4}",
      "\tpop\t{r0}",
      "\tbx\tr0",
      ".L_19b5c:",
      "\t.4byte\tgWarioData",
      "",
      ""
    ]
  },
  "func_8019B60": {
    "callees": [
      "func_8014C4C",
      "func_8014930",
      "func_80143D8",
      "func_8014758",
      "func_806DAC0",
      "func_8016614",
      "func_8014268",
      "func_801996C"
    ],
    "disasm": [
      "thumb_func_start func_8019B60",
      "func_8019B60:",
      "\tpush\t{r4, r5, r6, lr}",
      "\tsub\tsp, #4",
      "\tldr\tr4, .L_19bb8",
      "\tldr\tr2, .L_19bbc",
      "\tldr\tr3, .L_19bc0",
      "\tldrb\tr0, [r3, #1]",
      "\tlsl\tr0, r0, #3",
      "\tadd\tr1, r2, #4",
      "\tadd\tr0, r0, r1",
      "\tldrb\tr0, [r0, #0]",
      "\tstrb\tr0, [r4, #11]",
      "\tldrb\tr0, [r3, #1]",
      "\tlsl\tr0, r0, #3",
      "\tadd\tr1, r2, #5",
      "\tadd\tr0, r0, r1",
      "\tldrb\tr0, [r0, #0]",
      "\tstrb\tr0, [r4, #12]",
      "\tldrb\tr0, [r3, #1]",
      "\tlsl\tr0, r0, #3",
      "\tadd\tr1, r2, #6",
      "\tadd\tr0, r0, r1",
      "\tldrb\tr0, [r0, #0]",
      "\tstrb\tr0, [r4, #13]",
      "\tldrb\tr0, [r3, #1]",
      "\tlsl\tr0, r0, #3",
      "\tadd\tr2, #7",
      "\tadd\tr0, r0, r2",
      "\tldrb\tr0, [r0, #0]",
      "\tstrb\tr0, [r4, #17]",
      "\tmov\tr1, #24",
      "\tldrsh\tr0, [r3, r1]",
      "\tcmp\tr0, #47\t@ 0x2f",
      "\tbgt\t.L_19ba6",
      "\tmov\tr0, #0",
      "\tstrb\tr0, [r4, #12]",
      ".L_19ba6:",
      "\tmov\tr5, #255\t@ 0xff",
      "\tldrh\tr1, [r4, #2]",
      "\tmov\tr0, #64\t@ 0x40",
      "\tand\tr0, r1",
      "\tcmp\tr0, #0",
      "\tbeq\t.L_19bc4",
      "\tbl\tfunc_8014C4C",
      "\tb\t.L_19bf4",
      ".L_19bb8:",
      "\t.4byte\tgUnk_3001918",
      ".L_19bbc:",
      "\t.4byte\tsUnk_82DDA90",
      ".L_19bc0:",
      "\t.4byte\tgWarioData",
      ".L_19bc4:",
      "\tmov\tr0, #128\t@ 0x80",
      "\tand\tr0, r1",
      "\tcmp\tr0, #0",
      "\tbeq\t.L_19bd2",
      "\tbl\tfunc_8014930",
      "\tb\t.L_19bf4",
      ".L_19bd2:",
      "\tldrh\tr0, [r4, #0]",
      "\tcmp\tr0, #0",
      "\tbeq\t.L_19bea",
      "\tldrb\tr0, [r4, #17]",
      "\tcmp\tr0, #2",
      "\tbne\t.L_19be4",
      "\tbl\tfunc_8014930",
      "\tb\t.L_19bf4",
      ".L_19be4:",
      "\tbl\tfunc_80143D8",
      "\tb\t.L_19bf4",
      ".L_19bea:",
      "\tldrb\tr0, [r4, #17]",
      "\tcmp\tr0, #0",
      "\tbne\t.L_19bf8",
      "\tbl\tfunc_8014758",
      ".L_19bf4:",
      "\tlsl\tr0, r0, #24",
      "\tlsr\tr5, r0, #24",
      ".L_19bf8:",
      "\tldr\tr4, .L_19c20",
      "\tldrh\tr0, [r4, #20]",
      "\tsub\tr0, #48\t@ 0x30",
      "\tlsl\tr0, r0, #16",
      "\tlsr\tr0, r0, #16",
      "\tldrh\tr1, [r4, #18]",
      "\tbl\tfunc_806DAC0",
      "\tadd\tr1, r0, #0",
      "\tmov\tr0, #255\t@ 0xff",
      "\tand\tr1, r0",
      "\tcmp\tr1, #1",
      "\tbne\t.L_19c24",
      "\tstrb\tr1, [r4, #0]",
      "\tmov\tr0, #96\t@ 0x60",
      "\tstrb\tr0, [r4, #4]",
      "\tmov\tr0, #0",
      "\tbl\tfunc_8016614",
      "\tb\t.L_19c6e",
      ".L_19c20:",
      "\t.4byte\tgWarioData",
      ".L_19c24:",
      "\tldr\tr0, .L_19c3c",
      "\tldrb\tr1, [r0, #17]",
      "\tadd\tr6, r0, #0",
      "\tcmp\tr1, #255\t@ 0xff",
      "\tbeq\t.L_19c6e",
      "\tldrb\tr0, [r4, #1]",
      "\tcmp\tr0, #9",
      "\tbls\t.L_19c40",
      "\tcmp\tr5, #252\t@ 0xfc",
      "\tbne\t.L_19c40",
      "\tmov\tr5, #3",
      "\tb\t.L_19c64",
      ".L_19c3c:",
      "\t.4byte\tgUnk_3001918",
      ".L_19c40:",
      "\tldr\tr1, .L_19c78",
      "\tldrb\tr0, [r1, #1]",
      "\tcmp\tr0, #5",
      "\tbne\t.L_19c64",
      "\tcmp\tr5, #253\t@ 0xfd",
      "\tbne\t.L_19c64",
      "\tldrb\tr0, [r6, #8]",
      "\tldrh\tr1, [r1, #20]",
      "\tadd\tr1, #1",
      "\tlsl\tr1, r1, #16",
      "\tlsr\tr1, r1, #16",
      "\tmov\tr2, sp",
      "\tbl\tfunc_8014268",
      "\tldrb\tr6, [r6, #16]",
      "\tcmp\tr0, r6",
      "\tbgt\t.L_19c64",
      "\tmov\tr5, #255\t@ 0xff",
      ".L_19c64:",
      "\tcmp\tr5, #255\t@ 0xff",
      "\tbeq\t.L_19c6e",
      "\tadd\tr0, r5, #0",
      "\tbl\tfunc_801996C",
      ".L_19c6e:",
      "\tadd\tsp, #4",
      "\tpop\t{r4, r5, r6}",
      "\tpop\t{r0}",
      "\tbx\tr0",
      "\t.align\t2, 0",
      ".L_19c78:",
      "\t.4byte\tgWarioData",
      "",
      ""
    ]
  },
  "func_8019C7C": {
    "callees": [
      "func_800FF64",
      "func_800FD90"
    ],
    "disasm": [
      "thumb_func_start func_8019C7C",
      "func_8019C7C:",
      "\tpush\t{r4, lr}",
      "\tadd\tr4, r0, #0",
      "\tlsl\tr4, r4, #24",
      "\tlsr\tr4, r4, #24",
      "\tbl\tfunc_800FF64",
      "\tldr\tr1, .L_19ce0",
      "\tlsl\tr4, r4, #2",
      "\tldr\tr2, .L_19ce4",
      "\tldrb\tr0, [r2, #1]",
      "\tlsl\tr0, r0, #3",
      "\tadd\tr4, r4, r0",
      "\tadd\tr4, r4, r1",
      "\tldr\tr3, [r4, #0]",
      "\tldrb\tr1, [r2, #31]",
      "\tlsl\tr0, r1, #1",
      "\tadd\tr0, r0, r1",
      "\tlsl\tr0, r0, #2",
      "\tadd\tr3, r3, r0",
      "\tldr\tr1, [r3, #0]",
      "\tldrb\tr0, [r1, #0]",
      "\tlsl\tr0, r0, #5",
      "\tstrh\tr0, [r2, #40]\t@ 0x28",
      "\tadd\tr1, #1",
      "\tldrb\tr0, [r1, #0]",
      "\tlsl\tr0, r0, #5",
      "\tstrh\tr0, [r2, #48]\t@ 0x30",
      "\tadd\tr1, #1",
      "\tstr\tr1, [r2, #36]\t@ 0x24",
      "\tldrh\tr0, [r2, #40]\t@ 0x28",
      "\tadd\tr1, r1, r0",
      "\tstr\tr1, [r2, #44]\t@ 0x2c",
      "\tldr\tr0, [r3, #4]",
      "\tstr\tr0, [r2, #32]",
      "\tldr\tr1, .L_19ce8",
      "\tmov\tr0, #96\t@ 0x60",
      "\tstrh\tr0, [r1, #0]",
      "\tldr\tr0, .L_19cec",
      "\tmov\tr1, #0",
      "\tmov\tr2, #16",
      "\tbl\tfunc_800FD90",
      "\tldr\tr0, .L_19cf0",
      "\tmov\tr1, #16",
      "\tmov\tr2, #32",
      "\tbl\tfunc_800FD90",
      "\tpop\t{r4}",
      "\tpop\t{r0}",
      "\tbx\tr0",
      ".L_19ce0:",
      "\t.4byte\tsUnk_82DDA10",
      ".L_19ce4:",
      "\t.4byte\tgWarioData",
      ".L_19ce8:",
      "\t.4byte\tgWarioPaletteSize",
      ".L_19cec:",
      "\t.4byte\tsUnk_82DDDA0",
      ".L_19cf0:",
      "\t.4byte\tsUnk_82DE878",
      "",
      ""
    ]
  },
  "func_8019CF4": {
    "callees": [
      "m4aMPlayTempoControl",
      "m4aMPlayPitchControl",
      "m4aMPlayModDepthSet",
      "m4aMPlayLFOSpeedSet"
    ],
    "disasm": [
      "thumb_func_start func_8019CF4",
      "func_8019CF4:",
      "\tpush\t{r4, r5, r6, r7, lr}",
      "\tmov\tr7, r8",
      "\tpush\t{r7}",
      "\tldr\tr7, .L_19d6c",
      "\tmov\tr0, #0",
      "\tldrsb\tr0, [r7, r0]",
      "\tcmp\tr0, #10",
      "\tbeq\t.L_19d60",
      "\tldr\tr4, .L_19d70",
      "\tldr\tr6, [r4, #0]",
      "\tadd\tr0, r6, #0",
      "\tmov\tr1, #180\t@ 0xb4",
      "\tbl\tm4aMPlayTempoControl",
      "\tldr\tr4, [r4, #12]",
      "\tmov\tr8, r4",
      "\tmov\tr0, r8",
      "\tmov\tr1, #180\t@ 0xb4",
      "\tbl\tm4aMPlayTempoControl",
      "\tldr\tr4, .L_19d74",
      "\tldr\tr5, .L_19d78",
      "\tadd\tr0, r6, #0",
      "\tadd\tr1, r4, #0",
      "\tadd\tr2, r5, #0",
      "\tbl\tm4aMPlayPitchControl",
      "\tmov\tr0, r8",
      "\tadd\tr1, r4, #0",
      "\tadd\tr2, r5, #0",
      "\tbl\tm4aMPlayPitchControl",
      "\tadd\tr0, r6, #0",
      "\tadd\tr1, r4, #0",
      "\tmov\tr2, #20",
      "\tbl\tm4aMPlayModDepthSet",
      "\tmov\tr0, r8",
      "\tadd\tr1, r4, #0",
      "\tmov\tr2, #20",
      "\tbl\tm4aMPlayModDepthSet",
      "\tadd\tr0, r6, #0",
      "\tadd\tr1, r4, #0",
      "\tmov\tr2, #20",
      "\tbl\tm4aMPlayLFOSpeedSet",
      "\tmov\tr0, r8",
      "\tadd\tr1, r4, #0",
      "\tmov\tr2, #20",
      "\tbl\tm4aMPlayLFOSpeedSet",
      "\tmov\tr0, #10",
      "\tstrb\tr0, [r7, #0]",
      ".L_19d60:",
      "\tpop\t{r3}",
      "\tmov\tr8, r3",
      "\tpop\t{r4, r5, r6, r7}",
      "\tpop\t{r0}",
      "\tbx\tr0",
      "\t.align\t2, 0",
      ".L_19d6c:",
      "\t.4byte\tgUnk_30031BC",
      ".L_19d70:",
      "\t.4byte\tgMPlayTable",
      ".L_19d74:",
      "\t.4byte\t0xFFFF",
      ".L_19d78:",
      "\t.4byte\t0xFFFFFE0C",
      "",
      ""
    ]
  },
  "func_8019D7C": {
    "disasm": [
      "thumb_func_start func_8019D7C",
      "func_8019D7C:",
      "\tpush\t{r4, lr}",
      "\tldr\tr3, .L_19dc0",
      "\tldr\tr4, .L_19dc4",
      "\tldrb\tr0, [r4, #1]",
      "\tlsl\tr0, r0, #3",
      "\tadd\tr0, r0, r3",
      "\tldrb\tr1, [r0, #0]",
      "\tldr\tr2, .L_19dc8",
      "\tlsl\tr1, r1, #3",
      "\tadd\tr0, r1, r2",
      "\tldrh\tr0, [r0, #0]",
      "\tstrh\tr0, [r4, #50]\t@ 0x32",
      "\tadd\tr0, r2, #2",
      "\tadd\tr0, r1, r0",
      "\tldrh\tr0, [r0, #0]",
      "\tstrh\tr0, [r4, #52]\t@ 0x34",
      "\tadd\tr0, r2, #4",
      "\tadd\tr0, r1, r0",
      "\tldrh\tr0, [r0, #0]",
      "\tstrh\tr0, [r4, #54]\t@ 0x36",
      "\tadd\tr2, #6",
      "\tadd\tr1, r1, r2",
      "\tldrh\tr0, [r1, #0]",
      "\tstrh\tr0, [r4, #56]\t@ 0x38",
      "\tldrb\tr0, [r4, #1]",
      "\tlsl\tr0, r0, #3",
      "\tadd\tr3, #7",
      "\tadd\tr0, r0, r3",
      "\tldrb\tr0, [r0, #0]",
      "\tadd\tr1, r0, #0",
      "\tcmp\tr0, #2",
      "\tbne\t.L_19dcc",
      "\tstrb\tr0, [r4, #26]",
      "\tb\t.L_19dd4",
      ".L_19dc0:",
      "\t.4byte\tsUnk_82DDA90",
      ".L_19dc4:",
      "\t.4byte\tgWarioData",
      ".L_19dc8:",
      "\t.4byte\tsUnk_82DEB18",
      ".L_19dcc:",
      "\tldrb\tr0, [r4, #26]",
      "\tcmp\tr0, #1",
      "\tbeq\t.L_19dd4",
      "\tstrb\tr1, [r4, #26]",
      ".L_19dd4:",
      "\tpop\t{r4}",
      "\tpop\t{r0}",
      "\tbx\tr0",
      "\t.align\t2, 0"
    ]
  }
}